imessage_data_foundry/__init__.py
imessage_data_foundry/__main__.py
imessage_data_foundry/app.py
imessage_data_foundry/attachments/__init__.py
imessage_data_foundry/cli/__init__.py
imessage_data_foundry/cli/app.py
imessage_data_foundry/cli/menu.py
imessage_data_foundry/cli/provider_helper.py
imessage_data_foundry/cli/utils.py
imessage_data_foundry/cli/components/__init__.py
imessage_data_foundry/cli/components/autocomplete.py
imessage_data_foundry/cli/components/banner.py
imessage_data_foundry/cli/components/progress.py
imessage_data_foundry/cli/components/prompts.py
imessage_data_foundry/cli/components/tables.py
imessage_data_foundry/cli/flows/__init__.py
imessage_data_foundry/cli/flows/guided.py
imessage_data_foundry/cli/flows/manage.py
imessage_data_foundry/cli/flows/quick_start.py
imessage_data_foundry/cli/flows/settings.py
imessage_data_foundry/conversations/__init__.py
imessage_data_foundry/conversations/constants.py
imessage_data_foundry/conversations/generator.py
imessage_data_foundry/conversations/models.py
imessage_data_foundry/conversations/seeding.py
imessage_data_foundry/conversations/timestamps.py
imessage_data_foundry/db/__init__.py
imessage_data_foundry/db/addressbook.py
imessage_data_foundry/db/builder.py
imessage_data_foundry/db/validators.py
imessage_data_foundry/db/version_detect.py
imessage_data_foundry/db/schema/__init__.py
imessage_data_foundry/db/schema/addressbook.py
imessage_data_foundry/db/schema/base.py
imessage_data_foundry/db/schema/sequoia.py
imessage_data_foundry/db/schema/sonoma.py
imessage_data_foundry/db/schema/tahoe.py
imessage_data_foundry/llm/__init__.py
imessage_data_foundry/llm/anthropic_provider.py
imessage_data_foundry/llm/base.py
imessage_data_foundry/llm/config.py
imessage_data_foundry/llm/local_provider.py
imessage_data_foundry/llm/manager.py
imessage_data_foundry/llm/models.py
imessage_data_foundry/llm/openai_provider.py
imessage_data_foundry/llm/prompts.py
imessage_data_foundry/personas/__init__.py
imessage_data_foundry-1.0.0.dist-info/METADATA
imessage_data_foundry-1.0.0.dist-info/WHEEL
imessage_data_foundry-1.0.0.dist-info/entry_points.txt
imessage_data_foundry-1.0.0.dist-info/licenses/LICENSE
imessage_data_foundry-1.0.0.dist-info/RECORD
