Metadata-Version: 2.4
Name: imessage-data-foundry
Version: 1.0.0
Summary: Generate realistic, schema-accurate iMessage databases for testing and development
Project-URL: Homepage, https://github.com/johnlarkin1/imessage-data-foundry
Project-URL: Repository, https://github.com/johnlarkin1/imessage-data-foundry
Project-URL: Issues, https://github.com/johnlarkin1/imessage-data-foundry/issues
Author-email: John Larkin <john@johnjlarkin.com>
License: MIT License
License-File: LICENSE
Keywords: imessage,macos,mock-data,sqlite,testing
Classifier: Development Status :: 3 - Alpha
Classifier: Environment :: Console
Classifier: Intended Audience :: Developers
Classifier: License :: OSI Approved :: MIT License
Classifier: Operating System :: MacOS
Classifier: Programming Language :: Python :: 3
Classifier: Programming Language :: Python :: 3.11
Classifier: Programming Language :: Python :: 3.12
Classifier: Programming Language :: Python :: 3.13
Classifier: Topic :: Database
Classifier: Topic :: Software Development :: Testing
Requires-Python: >=3.11
Requires-Dist: anthropic>=0.18.0
Requires-Dist: faker>=24.0.0
Requires-Dist: huggingface-hub>=0.20.0
Requires-Dist: inquirerpy>=0.3.4
Requires-Dist: mlx-lm>=0.25.2; sys_platform == 'darwin'
Requires-Dist: openai>=1.12.0
Requires-Dist: phonenumbers>=8.13.0
Requires-Dist: psutil>=5.9.0
Requires-Dist: pydantic-settings>=2.2.0
Requires-Dist: pydantic>=2.6.0
Requires-Dist: rich>=13.7.0
Requires-Dist: textual>=0.47.0
Provides-Extra: dev
Requires-Dist: mypy>=1.8.0; extra == 'dev'
Requires-Dist: pytest-asyncio>=0.23.0; extra == 'dev'
Requires-Dist: pytest-cov>=4.1.0; extra == 'dev'
Requires-Dist: pytest>=8.0.0; extra == 'dev'
Requires-Dist: ruff>=0.3.0; extra == 'dev'
Requires-Dist: types-psutil>=5.9.0; extra == 'dev'
